wdbibtex/__init__.py
wdbibtex/__main__.py
wdbibtex/latex.py
wdbibtex/word.py
wdbibtex/tests/__init__.py
wdbibtex/tests/test_latex.py
wdbibtex-0.2.4.dist-info/LICENSE
wdbibtex-0.2.4.dist-info/METADATA
wdbibtex-0.2.4.dist-info/WHEEL
wdbibtex-0.2.4.dist-info/top_level.txt
wdbibtex-0.2.4.dist-info/RECORD
