Metadata-Version: 2.1
Name: wdbibtex
Version: 0.2.4
Summary: WdBibTeX is a BibTeX toolkit for MS Word.
Home-page: http://pypi.python.org/pypi/wdbibtex/
Author: Haruki EJIRI
Author-email: 0y35.ejiri.vmqewyhw@gmail.com
License: MIT
Project-URL: Document, https://ehki.github.io/WdBibTeX
Project-URL: Source, https://github.com/ehki/WdBibTeX
Platform: UNKNOWN
Classifier: Development Status :: 4 - Beta
Classifier: License :: OSI Approved :: MIT License
Classifier: Programming Language :: Python :: 3
Classifier: Operating System :: Microsoft
Classifier: Topic :: Text Editors :: Documentation
Classifier: Topic :: Text Editors :: Word Processors
Classifier: Topic :: Text Processing :: Markup :: LaTeX
Requires-Python: >=3.8
License-File: LICENSE
Requires-Dist: pywin32 (>=302)
Requires-Dist: regex (>=2022.6.2)
